apsbblib/__init__.py
apsbblib/__main__.py
apsbblib/arbitrator.py
apsbblib/device.py
apsbblib/jrpc.py
apsbblib/proxy.py
apsbblib/server.py
apsbblib/transport.py
apsbblib/utils.py
apsbblib/version.py
apsbblib/device_service/__init__.py
apsbblib/device_service/apsbb/__init__.py
apsbblib/device_service/apsbb/client.py
apsbblib/device_service/apsbb/common.py
apsbblib/device_service/apsbb/interface.py
apsbblib/device_service/apsbb/server.py
trimarlib_apsbb-0.2.3.dist-info/METADATA
trimarlib_apsbb-0.2.3.dist-info/RECORD
trimarlib_apsbb-0.2.3.dist-info/WHEEL
trimarlib_apsbb-0.2.3.dist-info/top_level.txt
