Metadata-Version: 2.1
Name: trimarlib-apsbb
Version: 0.2.3
Summary: APS Backbone Python wrapper for Linux host
Home-page: https://dsl2.trimar.org/pythons/apsbblib
Author: Kacper Kubkowski
Author-email: k.kubkowski@trimar.com.pl
License: UNKNOWN
Platform: UNKNOWN
Classifier: Development Status :: 1 - Planning
Classifier: Intended Audience :: Developers
Classifier: License :: OSI Approved :: MIT License
Classifier: Natural Language :: English
Classifier: Operating System :: POSIX :: Linux
Classifier: Programming Language :: Python :: 3 :: Only
Classifier: Programming Language :: Python :: Implementation :: CPython
Classifier: Topic :: Software Development :: Embedded Systems
Classifier: Topic :: System :: Hardware :: Hardware Drivers
Requires-Dist: pyserial
Requires-Dist: erpc (==1.6)
Requires-Dist: trimarlib-sysfsgpio
Requires-Dist: json-rpc
Requires-Dist: webcolors
